cursor_pagination.py
p3_django_cursor_pagination-0.1.5.dist-info/LICENSE
p3_django_cursor_pagination-0.1.5.dist-info/METADATA
p3_django_cursor_pagination-0.1.5.dist-info/WHEEL
p3_django_cursor_pagination-0.1.5.dist-info/top_level.txt
p3_django_cursor_pagination-0.1.5.dist-info/RECORD
