Metadata-Version: 2.1
Name: p3-django-cursor-pagination
Version: 0.1.5
Summary: Cursor based pagination for Django - Forked and fixed for Python 3 by Boris Lapouga
Home-page: https://github.com/boris-lapouga/django-cursor-pagination
Author: Photocrowd
Author-email: devteam@photocrowd.com
License: BSD
Platform: UNKNOWN
Classifier: Development Status :: 2 - Pre-Alpha
Classifier: Framework :: Django
Classifier: Intended Audience :: Developers
Classifier: License :: OSI Approved :: BSD License
Classifier: Natural Language :: English
Classifier: Programming Language :: Python :: 2
Classifier: Programming Language :: Python :: 2.7
Classifier: Programming Language :: Python :: 3
Classifier: Programming Language :: Python :: 3.4
Classifier: Programming Language :: Python :: 3.5
Classifier: Programming Language :: Python :: 3.6
Classifier: Programming Language :: Python :: 3.7
Classifier: Programming Language :: Python :: 3.8
